{
  "users": [
    {
      "name": "asif",
      "status": "Back-End Developer",
      "status1": "UI/UX Design",
      "Other": "",
      "text": "",
      "date": "",
      "num": "2",
      "id": 29
    },
    {
      "name": "asif",
      "status": "UI/UX Design",
      "status1": "",
      "Other": "",
      "text": "",
      "date": "2022-06-30",
      "num": "2",
      "id": 30
    },
    {
      "name": "cfcfgcg",
      "status": "qd",
      "status1": "",
      "Other": "fas",
      "text": "",
      "date": "",
      "num": "2",
      "id": 32
    },
    {
      "name": "asif",
      "status": "",
      "status1": "",
      "Other": "",
      "text": "",
      "date": "2022-06-30",
      "num": "2",
      "id": 33
    },
    {
      "name": "asifalibro",
      "status": "",
      "status1": "",
      "Other": "",
      "text": "",
      "date": "2022-06-24",
      "num": "2",
      "id": 34
    },
    {
      "name": "cfcfgcg",
      "status": "",
      "status1": "",
      "Other": "",
      "text": "",
      "date": "2022-06-30",
      "num": "2",
      "id": 35
    },
    {
      "name": "cfcfgcg",
      "status": "Front-End Developer",
      "status1": "Back-End Developer",
      "Other": "zxvz",
      "text": "xcgfcf",
      "date": "2022-06-29",
      "num": "23",
      "id": 36
    },
    {
      "name": "JANE",
      "status": "Back-End Developer",
      "status1": "Front-End Developer",
      "Other": "zxvz",
      "text": "asdadsas",
      "date": "2022-06-24",
      "num": "2",
      "id": 37
    }
  ]
}